looptick/__init__.py
looptick/core.py
looptick-0.1.4.dist-info/METADATA
looptick-0.1.4.dist-info/WHEEL
looptick-0.1.4.dist-info/licenses/LICENSE
looptick-0.1.4.dist-info/RECORD
