Metadata-Version: 2.4
Name: looptick
Version: 0.1.4
Summary: A simple loop execution time measurement tool.
Project-URL: Source, https://github.com/DBinK/LoopTick
Author-email: DBinK <DBinKv1d@Gmail.com>
License-File: LICENSE
Keywords: benchmark,loop,performance,profiling,timer
Classifier: Development Status :: 4 - Beta
Classifier: License :: OSI Approved :: MIT License
Classifier: Operating System :: OS Independent
Classifier: Programming Language :: Python :: 3
Classifier: Topic :: Software Development :: Debuggers
Classifier: Topic :: System :: Benchmark
Requires-Python: >=3.10
